LICENSE
skipper_lib/__init__.py
skipper_lib/__main__.py
skipper_lib/events/__init__.py
skipper_lib/events/event_producer.py
skipper_lib/events/event_receiver.py
skipper_lib/events/exchange_producer.py
skipper_lib/events/exchange_receiver.py
skipper_lib/logger/__init__.py
skipper_lib/logger/logger_helper.py
skipper_lib/workflow/__init__.py
skipper_lib/workflow/workflow_helper.py
skipper_lib-1.1.7.dist-info/entry_points.txt
skipper_lib-1.1.7.dist-info/LICENSE
skipper_lib-1.1.7.dist-info/WHEEL
skipper_lib-1.1.7.dist-info/METADATA
skipper_lib-1.1.7.dist-info/RECORD
