Metadata-Version: 2.1
Name: skipper-lib
Version: 1.1.7
Summary: Simple and flexible ML workflow engine
Home-page: https://github.com/katanaml/katana-skipper
License: Apache License
Keywords: machine learning,pipeline,rabbitmq
Author: Andrej Baranovskij
Author-email: andrejus.baranovskis@gmail.com
Requires-Python: >=3.7,<4.0
Classifier: License :: OSI Approved :: Apache Software License
Classifier: License :: Other/Proprietary License
Classifier: Operating System :: OS Independent
Classifier: Programming Language :: Python :: 3
Classifier: Programming Language :: Python :: 3.7
Classifier: Programming Language :: Python :: 3.8
Classifier: Programming Language :: Python :: 3.9
Classifier: Topic :: Software Development
Requires-Dist: pika (>=1.2.0,<2.0.0)
Requires-Dist: requests (>=2.25.1,<3.0.0)
Project-URL: Repository, https://github.com/katanaml/katana-skipper
